[
	{
		"inputs": [
			{
				"internalType": "string",
				"name": "title",
				"type": "string"
			},
			{
				"internalType": "string",
				"name": "content",
				"type": "string"
			}
		],
		"name": "addNote",
		"outputs": [],
		"stateMutability": "nonpayable",
		"type": "function"
	},
	{
		"inputs": [],
		"name": "getNotes",
		"outputs": [
			{
				"components": [
					{
						"internalType": "uint256",
						"name": "id",
						"type": "uint256"
					},
					{
						"internalType": "string",
						"name": "title",
						"type": "string"
					},
					{
						"internalType": "string",
						"name": "content",
						"type": "string"
					}
				],
				"internalType": "struct Notes.note[]",
				"name": "",
				"type": "tuple[]"
			}
		],
		"stateMutability": "view",
		"type": "function"
	},
	{
		"inputs": [
			{
				"internalType": "uint256",
				"name": "id",
				"type": "uint256"
			}
		],
		"name": "removeNote",
		"outputs": [],
		"stateMutability": "nonpayable",
		"type": "function"
	}
]